ironman/__init__.py
ironman/communicator.py
ironman/globals.py
ironman/hardware.py
ironman/history.py
ironman/interfaces.py
ironman/packet.py
ironman/server.py
ironman/utilities.py
ironman/version.py
ironman/constructs/__init__.py
ironman/constructs/ipbus.py
ironman-0.6.0.dist-info/LICENSE
ironman-0.6.0.dist-info/METADATA
ironman-0.6.0.dist-info/WHEEL
ironman-0.6.0.dist-info/top_level.txt
ironman-0.6.0.dist-info/RECORD
