Metadata-Version: 2.1
Name: ironman
Version: 0.6.0
Summary: SoC Firmware for L1Calo
Home-page: https://github.com/kratsg/ironman
Author: Giordon Stark, Emily Smith
Author-email: gstark@cern.ch, emsmith@cern.ch
License: MIT
Project-URL: Documentation, https://ironman.readthedocs.io/
Project-URL: Source, https://github.com/kratsg/ironman
Project-URL: Tracker, https://github.com/krasg/ironman/issues
Keywords: physics software-on-chip SoC bitbake slow-control ipbus
Platform: UNKNOWN
Classifier: Development Status :: 4 - Beta
Classifier: Natural Language :: English
Classifier: Operating System :: POSIX :: Linux
Classifier: Intended Audience :: Developers
Classifier: License :: OSI Approved :: MIT License
Classifier: Intended Audience :: Science/Research
Classifier: Topic :: Scientific/Engineering
Classifier: Topic :: Scientific/Engineering :: Physics
Classifier: Topic :: System :: Hardware
Classifier: Programming Language :: Python :: 3
Classifier: Programming Language :: Python :: 3 :: Only
Classifier: Programming Language :: Python :: 3.7
Classifier: Programming Language :: Python :: 3.8
Classifier: Programming Language :: Python :: Implementation :: CPython
Requires-Python: >=3.7
License-File: LICENSE
Requires-Dist: Twisted (>=15.4.0)
Requires-Dist: zope.interface (==4.1.3)
Requires-Dist: construct (==2.9.39)
Requires-Dist: pyyaml (>=4.2b1)
Provides-Extra: complete
Requires-Dist: Sphinx (<4) ; extra == 'complete'
Requires-Dist: black ; extra == 'complete'
Requires-Dist: bump2version ; extra == 'complete'
Requires-Dist: check-manifest ; extra == 'complete'
Requires-Dist: flake8 ; extra == 'complete'
Requires-Dist: pre-commit ; extra == 'complete'
Requires-Dist: pytest-cov (>=2.5.1) ; extra == 'complete'
Requires-Dist: pytest (~=6.0) ; extra == 'complete'
Requires-Dist: repoze.sphinx.autointerface ; extra == 'complete'
Requires-Dist: sphinx-rtd-theme ; extra == 'complete'
Requires-Dist: twine ; extra == 'complete'
Provides-Extra: develop
Requires-Dist: Sphinx (<4) ; extra == 'develop'
Requires-Dist: black ; extra == 'develop'
Requires-Dist: bump2version ; extra == 'develop'
Requires-Dist: check-manifest ; extra == 'develop'
Requires-Dist: flake8 ; extra == 'develop'
Requires-Dist: pre-commit ; extra == 'develop'
Requires-Dist: pytest-cov (>=2.5.1) ; extra == 'develop'
Requires-Dist: pytest (~=6.0) ; extra == 'develop'
Requires-Dist: repoze.sphinx.autointerface ; extra == 'develop'
Requires-Dist: sphinx-rtd-theme ; extra == 'develop'
Requires-Dist: twine ; extra == 'develop'
Provides-Extra: docs
Requires-Dist: Sphinx (<4) ; extra == 'docs'
Requires-Dist: sphinx-rtd-theme ; extra == 'docs'
Requires-Dist: repoze.sphinx.autointerface ; extra == 'docs'
Provides-Extra: lint
Requires-Dist: black ; extra == 'lint'
Requires-Dist: flake8 ; extra == 'lint'
Provides-Extra: test
Requires-Dist: pytest (~=6.0) ; extra == 'test'
Requires-Dist: pytest-cov (>=2.5.1) ; extra == 'test'
